readability_improver/__init__.py
readability_improver/readability_improver.py
readability_improver-1.0.1.dist-info/entry_points.txt
readability_improver-1.0.1.dist-info/WHEEL
readability_improver-1.0.1.dist-info/METADATA
readability_improver-1.0.1.dist-info/RECORD
