Metadata-Version: 2.1
Name: readability-improver
Version: 1.0.1
Summary: Remove all your magic numbers and make your code 1000% more readable!
License: lmao
Author: Eric Udlis
Author-email: udlis.eric@gmail.com
Requires-Python: >=3.8,<4.0
Classifier: License :: Other/Proprietary License
Classifier: Programming Language :: Python :: 3
Classifier: Programming Language :: Python :: 3.8
Classifier: Programming Language :: Python :: 3.9
Requires-Dist: num2words (>=0.5.12,<0.6.0)
